[
  {
    "delete": "user",
    "deletes": [
      { "q": { "_id": { "$oid": "64b7f345c21a9b1f12345601" } }, "limit": 1 },
      { "q": { "_id": { "$oid": "64b7f345c21a9b1f12345602" } }, "limit": 1 },
      { "q": { "_id": { "$oid": "64b7f345c21a9b1f12345603" } }, "limit": 1 },
      { "q": { "_id": { "$oid": "64b7f345c21a9b1f12345604" } }, "limit": 1 },
      { "q": { "_id": { "$oid": "64b7f345c21a9b1f12345605" } }, "limit": 1 },

      { "q": { "_id": { "$oid": "74c2d987a19a4c2f82345601" } }, "limit": 1 },
      { "q": { "_id": { "$oid": "74c2d987a19a4c2f82345602" } }, "limit": 1 },
      { "q": { "_id": { "$oid": "74c2d987a19a4c2f82345603" } }, "limit": 1 },
      { "q": { "_id": { "$oid": "74c2d987a19a4c2f82345604" } }, "limit": 1 },
      { "q": { "_id": { "$oid": "74c2d987a19a4c2f82345605" } }, "limit": 1 },

      { "q": { "_id": { "$oid": "64b7f345c21a9b1f1234abcd" } }, "limit": 1 },
      { "q": { "_id": { "$oid": "74c2d987a19a4c2f8234abcd" } }, "limit": 1 }
    ]
  }
]